DESCRIPTION.rst
LICENSE
MANIFEST.in
README.rst
setup.cfg
setup.py
daemon/marcod.service
daemon/polod.service
daemon/poloreload.py
daemon/polostart.py
daemon/python3/marcod.service
daemon/python3/polod.service
daemon/python3/poloreload.py
daemon/python3/polostart.py
daemon/python3/systemv/marcod
daemon/python3/systemv/polod
daemon/systemv/marcod
daemon/systemv/polod
daemon/twistd/marco_twistd.tac
daemon/twistd/polo_twistd.tac
etc/marcopolo/certs/polossl.crt
etc/marcopolo/certs/polossl.key
etc/marcopolo/marco/marco.cfg
etc/marcopolo/polo/polo.cfg
etc/marcopolo/polo/secret
etc/marcopolo/polo/services/skel
etc/marcopolo/polo/services/skelwithmoreoptions
marcopolo/__init__.py
marcopolo.egg-info/PKG-INFO
marcopolo.egg-info/SOURCES.txt
marcopolo.egg-info/dependency_links.txt
marcopolo.egg-info/entry_points.txt
marcopolo.egg-info/namespace_packages.txt
marcopolo.egg-info/not-zip-safe
marcopolo.egg-info/requires.txt
marcopolo.egg-info/top_level.txt
marcopolo/marco/__init__.py
marcopolo/marco/conf.py
marcopolo/marco/marco.py
marcopolo/marco/marcobinding.py
marcopolo/marco/marcod.py
marcopolo/marco_conf/__init__.py
marcopolo/marco_conf/utils.py
marcopolo/polo/__init__.py
marcopolo/polo/__main__.py
marcopolo/polo/conf.py
marcopolo/polo/polo.py
marcopolo/polo/polobinding.py
marcopolo/polo/polobindingssl.py
marcopolo/polo/polod.py
marcopolo/polo/tokenprovider.py
marcopolo/tests/__init__.py
marcopolo/tests/test.py
marcopolo/tests/test_marco.py
marcopolo/tests/test_marco_binding.py
marcopolo/tests/test_polo.py
marcopolo/tests/test_polo_binding.py