Metadata-Version: 1.1
Name: marcopolo
Version: 0.1.7
Summary: The reference implementation for MarcoPolo
Home-page: marcopolo.martinarroyo.net
Author: Diego Martín
Author-email: martinarroyo@usal.es
License: MIT
Download-URL: https://bitbucket.org/Alternhuman/marcopolo/get/v0.1.7.tar.gz
Keywords: marcopolo discovery binding
Platform: UNKNOWN
Classifier: Development Status :: 3 - Alpha
Classifier: Intended Audience :: Developers
Classifier: Intended Audience :: System Administrators
Classifier: Topic :: Software Development :: Build Tools
Classifier: Topic :: System :: Networking
Classifier: License :: OSI Approved :: Mozilla Public License 2.0 (MPL 2.0)
Classifier: Programming Language :: Python :: 2.7
Classifier: Programming Language :: Python :: 3.4
Classifier: Natural Language :: English
Provides: marcopolo.marco
Provides: marcopolo.polo
